flask_sentry/__init__.py
flask_sentry-0.2.0.dist-info/WHEEL
flask_sentry-0.2.0.dist-info/METADATA
flask_sentry-0.2.0.dist-info/RECORD
