Metadata-Version: 2.4
Name: flask-sentry
Version: 0.2.0
Summary: Sentry and Spotlight integration for Flask
Author: Maxime Bouroumeau-Fuseau
Author-email: Maxime Bouroumeau-Fuseau <maxime.bouroumeau@gmail.com>
License-Expression: MIT
Requires-Dist: flask>=3.0.0,<4.0.0
Requires-Dist: sentry-sdk[flask]>=2.0.1,<3.0.0
Requires-Python: >=3.10
Project-URL: Repository, https://github.com/hyperflask/flask-sentry
